{
  "/favicon.ico/route": "app/favicon.ico/route.js",
  "/page": "app/page.js",
  "/Blog/page": "app/Blog/page.js",
  "/About/page": "app/About/page.js",
  "/Categories/page": "app/Categories/page.js",
  "/Coming-soon/page": "app/Coming-soon/page.js",
  "/Products/page": "app/Products/page.js",
  "/Contact/page": "app/Contact/page.js",
  "/Products/Ojuset/page": "app/Products/Ojuset/page.js",
  "/Products/Kurol/page": "app/Products/Kurol/page.js",
  "/Products/Ojuset/benefits/[id]/page": "app/Products/Ojuset/benefits/[id]/page.js"
}